README.rst
setup.py
wspaceping/__init__.py
wspaceping/browser.py
wspaceping/cli.py
wspaceping/constants.py
wspaceping/poller.py
wspaceping/session.py
wspaceping.egg-info/PKG-INFO
wspaceping.egg-info/SOURCES.txt
wspaceping.egg-info/dependency_links.txt
wspaceping.egg-info/entry_points.txt
wspaceping.egg-info/requires.txt
wspaceping.egg-info/top_level.txt