Metadata-Version: 1.0
Name: wspaceping
Version: 0.1
Summary: Watch the EVE Online Wormhole mapper siggy for new connections.
Home-page: https://github.com/ikanobori
Author: Simon de Vlieger
Author-email: simon@ikanobori.jp
License: UNKNOWN
Platform: UNKNOWN
